ansitohtml/__init__.py
ansitohtml/parser.py
ansitohtml/theme.py
ansitohtml-0.1.4.dist-info/LICENSE
ansitohtml-0.1.4.dist-info/METADATA
ansitohtml-0.1.4.dist-info/WHEEL
ansitohtml-0.1.4.dist-info/RECORD
